qasm/qasm.py
qasm-0.0.2.dist-info/METADATA
qasm-0.0.2.dist-info/RECORD
qasm-0.0.2.dist-info/WHEEL
qasm-0.0.2.dist-info/top_level.txt
