Metadata-Version: 2.1
Name: qasm
Version: 0.0.2
Summary: Parser for OPENQASM and cQASM
Home-page: https://github.com/qevedo/qasm
Author: Alex
Author-email: alxmorais8@msn.com
License: Apache License
